
{
  "data": [
    {
      "link": "https://amg-info-space.nyc3.cdn.digitaloceanspaces.com/saconst%2FIMG_2364.JPG",
      "alt": "Roofing, siding, and trim project."
    },
    {
      "link": "https://amg-info-space.nyc3.cdn.digitaloceanspaces.com/saconst%2FIMG_2370.JPG",
      "alt": "Residential home trim project."
    },
    {
      "link": "https://amg-info-space.nyc3.cdn.digitaloceanspaces.com/saconst%2FResized_20220511_112532.JPEG",
      "alt": "Residential roofing project."
    },
    {
      "link": "https://amg-info-space.nyc3.cdn.digitaloceanspaces.com/saconst%2FResized_20211124_114610.JPEG",
      "alt": "Residential trim project."
    },
    {
      "link": "https://amg-info-space.nyc3.cdn.digitaloceanspaces.com/saconst%2FResized_20220516_102349.JPEG",
      "alt": "Residential roofing project."
    }
  ]
}